tuya_sharing/__init__.py
tuya_sharing/const.py
tuya_sharing/custom_strategy.py
tuya_sharing/customerapi.py
tuya_sharing/customerlogging.py
tuya_sharing/device.py
tuya_sharing/home.py
tuya_sharing/manager.py
tuya_sharing/mq.py
tuya_sharing/scenes.py
tuya_sharing/strategy.py
tuya_sharing/user.py
tuya_sharing/version.py
tuya_sharing/strategy_repo/__init__.py
tuya_sharing/strategy_repo/cz_timer1_alg.py
tuya_sharing/strategy_repo/cz_timer2_alg.py
tuya_sharing/strategy_repo/db_v1_alarm.py
tuya_sharing/strategy_repo/db_v1_daily.py
tuya_sharing/strategy_repo/db_v1_data.py
tuya_sharing/strategy_repo/db_v1_frozen.py
tuya_sharing/strategy_repo/db_v1_month.py
tuya_sharing/strategy_repo/db_v1_params.py
tuya_sharing/strategy_repo/db_v1_tariff.py
tuya_sharing/strategy_repo/default.py
tuya_sharing/strategy_repo/dj_v1_hsv_alg.py
tuya_sharing/strategy_repo/dj_v1_scene_alg.py
tuya_sharing/strategy_repo/dj_v2_color_alg.py
tuya_sharing/strategy_repo/dj_v2_contr_alg.py
tuya_sharing/strategy_repo/dj_v2_music_alg.py
tuya_sharing/strategy_repo/dj_v2_scene_alg.py
tuya_sharing/strategy_repo/enum_.py
tuya_sharing/strategy_repo/hb_djv1_color.py
tuya_sharing/strategy_repo/hb_jsq_lightv1.py
tuya_sharing/strategy_repo/hb_range_v1.py
tuya_sharing/strategy_repo/hb_range_v2.py
tuya_sharing/strategy_repo/ms_dp_syn_alg.py
tuya_sharing/strategy_repo/sd_clean_record.py
tuya_sharing/strategy_repo/voice_atm_color.py
tuya_device_sharing_sdk-0.2.5.dist-info/LICENSE
tuya_device_sharing_sdk-0.2.5.dist-info/METADATA
tuya_device_sharing_sdk-0.2.5.dist-info/WHEEL
tuya_device_sharing_sdk-0.2.5.dist-info/top_level.txt
tuya_device_sharing_sdk-0.2.5.dist-info/RECORD
