Metadata-Version: 2.1
Name: tuya-device-sharing-sdk
Version: 0.2.5
Summary: A Python sdk for Tuya Open API, which provides IoT capabilities, maintained by Tuya official
Home-page: https://github.com/tuya/tuya-device-sharing-sdk
Author: Tuya Inc.
Author-email: developer@tuya.com
License: MIT
Project-URL: Bug Tracker, https://github.com/tuya/tuya-device-sharing-sdk/issues
Project-URL: Changes, https://github.com/tuya/tuya-device-sharing-sdk/wiki/Tuya-Device-Sharing-SDK-Release-Notes
Keywords: tuya device sdk python
Classifier: Development Status :: 4 - Beta
Classifier: License :: OSI Approved :: MIT License
Classifier: Operating System :: OS Independent
Classifier: Topic :: Software Development
Classifier: Programming Language :: Python :: 3
Classifier: Programming Language :: Python :: 3.7
Classifier: Programming Language :: Python :: 3.8
Classifier: Programming Language :: Python :: 3.9
Classifier: Programming Language :: Python :: 3.10
Classifier: Programming Language :: Python :: Implementation :: PyPy
Requires-Python: >=3.7
License-File: LICENSE
Requires-Dist: paho-mqtt
Requires-Dist: requests
